rmc/__init__.py
rmc/cli.py
rmc/qrmc.ui
rmc/rmc_common.py
rmc/tui.css
rmc/tui.py
rmc/ui.py
rm_commander-0.3.0.dev1.dist-info/METADATA
rm_commander-0.3.0.dev1.dist-info/WHEEL
rm_commander-0.3.0.dev1.dist-info/entry_points.txt
rm_commander-0.3.0.dev1.dist-info/RECORD
