Metadata-Version: 2.1
Name: rm-commander
Version: 0.3.0.dev1
Summary: reMarkable Commander
Home-page: https://projects.om-office.de/frans/rmc.git
Author: Frans Fürst
Author-email: frans.fuerst+gitlab@protonmail.com
Requires-Python: >=3.10.4,<4.0.0
Classifier: Programming Language :: Python :: 3
Classifier: Programming Language :: Python :: 3.11
Classifier: Programming Language :: Python :: 3.12
Requires-Dist: asyncssh (>=2.14.2,<3.0.0)
Requires-Dist: lxml (>=4.7,<5.0)
Requires-Dist: pdfkit (>=1.0.0,<2.0.0)
Requires-Dist: pydantic (>=2.9.0,<3.0.0)
Requires-Dist: pyhtml2pdf (>=0.0.7,<0.0.8)
Requires-Dist: rich (>=13.8.0,<14.0.0)
Requires-Dist: ruff (>=0.6.4,<0.7.0)
Requires-Dist: textual (>=0.82,<0.83)
Requires-Dist: trickkiste (==0.1.6)
Requires-Dist: weasyprint (>=61.2,<62.0)
Requires-Dist: wkhtmltopdf (>=0.2,<0.3)
Project-URL: Repository, https://projects.om-office.de/frans/rmc.git
